aracnid_utils/__init__.py
aracnid_utils/datetime_utils.py
aracnid_utils-1.0.4.dist-info/LICENSE
aracnid_utils-1.0.4.dist-info/WHEEL
aracnid_utils-1.0.4.dist-info/METADATA
aracnid_utils-1.0.4.dist-info/RECORD
