Metadata-Version: 2.1
Name: aracnid-utils
Version: 1.0.4
Summary: Common custom utility functions
Home-page: https://github.com/aracnid/aracnid-utils
License: MIT
Keywords: python,utils
Author: Jason Romano
Author-email: aracnid@gmail.com
Requires-Python: >=3.10,<4.0
Classifier: License :: OSI Approved :: MIT License
Classifier: Programming Language :: Python :: 3
Classifier: Programming Language :: Python :: 3.10
Classifier: Programming Language :: Python :: 3.11
Requires-Dist: aracnid-logger (>=1.0,<2.0)
Requires-Dist: python-dateutil (>=2.8,<3.0)
Requires-Dist: pytz (>=2022.2,<2023.0)
Project-URL: Repository, https://github.com/aracnid/aracnid-utils
